pdf_qa/__init__.py
pdf_qa/pdf_qa.py
pdf_qa-0.1.7.dist-info/METADATA
pdf_qa-0.1.7.dist-info/WHEEL
pdf_qa-0.1.7.dist-info/entry_points.txt
pdf_qa-0.1.7.dist-info/top_level.txt
pdf_qa-0.1.7.dist-info/RECORD
