Metadata-Version: 2.1
Name: pdf_qa
Version: 0.1.7
Summary: A PDF question answering tool using various LLMs
Home-page: https://github.com/umutbozdag/pdf_qa
Author: Umut
Author-email: contact@umutbozdag.com
Classifier: Programming Language :: Python :: 3
Classifier: License :: OSI Approved :: MIT License
Classifier: Operating System :: OS Independent
Requires-Python: >=3.6
